.gitignore
requirements.txt
setup.py
mqtool/__init__.py
mqtool/utils.py
mqtool.egg-info/PKG-INFO
mqtool.egg-info/SOURCES.txt
mqtool.egg-info/dependency_links.txt
mqtool.egg-info/not-zip-safe
mqtool.egg-info/requires.txt
mqtool.egg-info/top_level.txt
mqtool/kit/__init__.py
mqtool/kit/kafka_kit.py
mqtool/kit/tornado_server.py
mqtool/model/__init__.py
mqtool/model/main.py