Metadata-Version: 1.1
Name: mqtool
Version: 1.0.5
Summary: bq tool
Home-page: UNKNOWN
Author: BussanQ
Author-email: UNKNOWN
License: BussanQ
Platform: UNKNOWN
Classifier: Programming Language :: Python
Classifier: Operating System :: Microsoft :: Windows
Classifier: Operating System :: Unix
Classifier: Programming Language :: Python :: 3
